reposcraping/__init__.py
reposcraping/cloner.py
reposcraping-1.1.7.dist-info/LICENSE
reposcraping-1.1.7.dist-info/METADATA
reposcraping-1.1.7.dist-info/WHEEL
reposcraping-1.1.7.dist-info/top_level.txt
reposcraping-1.1.7.dist-info/RECORD
