Metadata-Version: 2.1
Name: reposcraping
Version: 1.1.7
Summary: Scraping GitHub repository
Home-page: https://github.com/emresvd/reposcraping
Author: emresvd
License: MIT
Keywords: github,scraping,repository,clone
Classifier: Development Status :: 5 - Production/Stable
Classifier: Intended Audience :: Developers
Classifier: License :: OSI Approved :: MIT License
Classifier: Natural Language :: English
Classifier: Programming Language :: Python :: 3
Classifier: Topic :: Software Development :: Libraries :: Python Modules
Classifier: Operating System :: OS Independent
License-File: LICENSE
Requires-Dist: beautifulsoup4 (==4.11.1)
Requires-Dist: requests (==2.28.1)
